keycloak_api/__init__.py
keycloak_api/api_client.py
keycloak_api/configuration.py
keycloak_api/exceptions.py
keycloak_api/model_utils.py
keycloak_api/rest.py
keycloak_api/api/__init__.py
keycloak_api/api/attack_detection_api.py
keycloak_api/api/authentication_management_api.py
keycloak_api/api/client_attribute_certificate_api.py
keycloak_api/api/client_initial_access_api.py
keycloak_api/api/client_registration_policy_api.py
keycloak_api/api/client_role_mappings_api.py
keycloak_api/api/client_scopes_api.py
keycloak_api/api/clients_api.py
keycloak_api/api/component_api.py
keycloak_api/api/groups_api.py
keycloak_api/api/identity_providers_api.py
keycloak_api/api/key_api.py
keycloak_api/api/protocol_mappers_api.py
keycloak_api/api/realms_admin_api.py
keycloak_api/api/role_mapper_api.py
keycloak_api/api/roles_api.py
keycloak_api/api/roles_by_id_api.py
keycloak_api/api/root_api.py
keycloak_api/api/scope_mappings_api.py
keycloak_api/api/user_storage_provider_api.py
keycloak_api/api/users_api.py
keycloak_api/apis/__init__.py
keycloak_api/model/__init__.py
keycloak_api/model/access_token.py
keycloak_api/model/access_token_access.py
keycloak_api/model/access_token_authorization.py
keycloak_api/model/access_token_cert_conf.py
keycloak_api/model/address_claim_set.py
keycloak_api/model/authentication_execution_export_representation.py
keycloak_api/model/authentication_execution_info_representation.py
keycloak_api/model/authentication_execution_representation.py
keycloak_api/model/authentication_flow_representation.py
keycloak_api/model/authenticator_config_info_representation.py
keycloak_api/model/authenticator_config_representation.py
keycloak_api/model/certificate_representation.py
keycloak_api/model/client_initial_access_create_presentation.py
keycloak_api/model/client_initial_access_presentation.py
keycloak_api/model/client_mappings_representation.py
keycloak_api/model/client_policies_representation.py
keycloak_api/model/client_policy_condition_representation.py
keycloak_api-17.0.post2.dist-info/METADATA
keycloak_api-17.0.post2.dist-info/WHEEL
keycloak_api-17.0.post2.dist-info/top_level.txt
keycloak_api-17.0.post2.dist-info/RECORD
