Metadata-Version: 2.1
Name: keycloak-api
Version: 17.0.post2
Summary: Keycloak Admin REST API
Home-page: 
Author: OpenAPI Generator community
Author-email: team@openapitools.org
License: UNKNOWN
Keywords: OpenAPI,OpenAPI-Generator,Keycloak Admin REST API
Platform: UNKNOWN
Requires-Python: >=3.6
Requires-Dist: urllib3 (>=1.25.3)
Requires-Dist: python-dateutil
